cr_agent/__init__.py
cr_agent/graph.py
cr_agent/main.py
cr_agent/seed.py
cr_agent/state.py
cr_agent/agents/__init__.py
cr_agent/agents/domain_agent.py
cr_agent/agents/general_reviewer.py
cr_agent/agents/output_parsers.py
cr_agent/agents/performance_agent.py
cr_agent/agents/security_agent.py
cr_agent/routing/__init__.py
cr_agent/routing/file_filter.py
cr_agent/routing/router.py
cr_agent/tools/__init__.py
cr_agent/tools/dependency_impact.py
cr_agent/tools/design_patterns.py
cr_agent/tools/hotspot_detector.py
cr_agent/tools/user_preferences.py
zerog_cr-0.1.0.dist-info/METADATA
zerog_cr-0.1.0.dist-info/WHEEL
zerog_cr-0.1.0.dist-info/entry_points.txt
zerog_cr-0.1.0.dist-info/licenses/LICENSE
zerog_cr-0.1.0.dist-info/RECORD
