Metadata-Version: 2.4
Name: zerog-cr
Version: 0.1.0
Summary: Zero-G Reviewer: AI Code Review Agent using LangGraph
License-Expression: MIT
License-File: LICENSE
Requires-Python: >=3.11
Requires-Dist: chromadb>=0.5.0
Requires-Dist: gitpython>=3.1.0
Requires-Dist: langchain-core>=0.3.0
Requires-Dist: langchain-openai>=0.2.0
Requires-Dist: langgraph>=0.2.0
Requires-Dist: pydantic>=2.0.0
Requires-Dist: pygithub>=2.0.0
Requires-Dist: python-gitlab>=4.0.0
Requires-Dist: sentence-transformers>=3.0.0
Provides-Extra: dev
Requires-Dist: build>=1.4.0; extra == 'dev'
Requires-Dist: pytest-asyncio>=0.24.0; extra == 'dev'
Requires-Dist: pytest>=8.0.0; extra == 'dev'
Requires-Dist: twine>=6.2.0; extra == 'dev'
